{
  "tittel": "Orienteringer",
  "innstilling": "Orienteringene tas til etterretning.",
  "vedtak": "Orienteringene tas til etterretning.",
  "alternative_forslag": [],
  "voteringer": [
    {
      "beskrivelse": "Kommunedirektørens forslag til vedtak",
      "alternativer": [
        {
          "navn": "For",
          "stemmer": "enstemmig"
        }
      ],
      "hvem_vant": "For",
      "roedt_stoettet": "For",
      "roedt_paa_vinner_side": true
    }
  ],
  "kommune": "røros",
  "dato": "24.04.2025",
  "saksnummer_ps": "PS 025/25",
  "rodt_fremmet_forslag": false
}