{
  "tittel": "018/25 Klagebehandling- reguleringsplan Ysterhagaen barnehage",
  "innstilling": [
    "1. Klagene tas ikke til følge. Saken sendes til Statsforvalteren til sluttbehandling",
    "2. Klagene gis ikke utsettende virkning etter forvaltningslovens § 42."
  ],
  "vedtak": [
    "1. Klagene tas ikke til følge. Saken sendes til Statsforvalteren til sluttbehandling",
    "2. Klagene gis ikke utsettende virkning etter forvaltningslovens § 42.",
    "3. Kommunestyret ber kommunedirektøren varsle oppstart av arbeid med endring av reguleringsplan for Ysterhagaen barnehage (planid 20220008). Formålet med planarbeidet skal være å vurdere en omregulering av o_P3 til grøntareal samt skjermingstiltak for Ysterhagveien nr. 17."
  ],
  "alternative_forslag": [
    {
      "forslagsstiller": "Repr. Jon Anders Kokkvoll (Ap)",
      "tekst": "…. samt skjermingstiltak for Ysterhagveien nr. 17."
    }
  ],
  "voteringer": [
    {
      "beskrivelse": "Innstillingen i saken og tilleggspunkt fra repr. Kokkvoll til pkt 3 i innstillingen",
      "alternativer": [
        {
          "navn": "Enstemmig vedtatt",
          "stemmer": "alle"
        }
      ],
      "hvem_vant": "Enstemmig vedtatt",
      "roedt_stoettet": "Enstemmig vedtatt",
      "roedt_paa_vinner_side": true
    }
  ],
  "kommune": "røros",
  "dato": "27.03.2025",
  "saksnummer_ps": "PS 018/25",
  "rodt_fremmet_forslag": false
}