{
  "tittel": "Håkon Magnussons gate 9, detaljregulering - sluttbehandling",
  "innstilling": null,
  "vedtak": "Saken ble utsatt i bystyrets møte 27. mars 2025.",
  "alternative_forslag": [],
  "voteringer": [
    {
      "beskrivelse": "Votering over utsettelse av saken.",
      "alternativer": [
        {
          "navn": "Utsette saken",
          "stemmer": null
        },
        {
          "navn": "Ikke utsette saken",
          "stemmer": null
        }
      ],
      "hvem vant": "Utsette saken",
      "hvilket alternativ Rødt støttet": null,
      "om Rødt var på vinner- eller taper-side": null
    }
  ],
  "kommune": "trondheim",
  "dato": "27.03.2025",
  "saksnummer_ps": "PS 66/2025",
  "rodt_fremmet_forslag": false
}