{
  "tittel": "PS 18/25 Lovlighetskontroll av vedtak i sak PS 10/2025 - Forskrift om skolekretsgrenser i Verdal kommune",
  "innstilling": "Kommunedirektørens forslag til vedtak",
  "vedtak": "Vedtak i sak PS 10/2025 opprettholdes.\nSaken med alle vedlegg, sendes til Statsforvalter for lovlighetskontroll av vedtaket.\nKommunestyret ber Statsforvalteren vurdere sin habilitet, da Stasforvalteren har vært inne i saken.",
  "alternative_forslag": [
    {
      "forslagsstiller": "H, SP, VDL og FRP (fremmet av Hilde Daleng (SP))",
      "tekst": "Vedtak i sak PS 10/2025 opprettholdes.\nSaken med alle vedlegg, sendes til Statsforvalter for lovlighetskontroll av vedtaket.\nKommunestyret ber Statsforvalteren vurdere sin habilitet, da Stasforvalteren har vært inne i saken."
    }
  ],
  "voteringer": [
    {
      "beskrivelse": "Alternativ votering mellom kommunedirektørens forslag til vedtak og forslaget fra H, SP, VDL og FRP",
      "alternativer": [
        {
          "navn": "Forslaget fra H, SP, VDL og FRP",
          "stemmer": 28
        },
        {
          "navn": "Kommunedirektørens forslag til vedtak",
          "stemmer": 7
        }
      ],
      "hvem_vant": "Forslaget fra H, SP, VDL og FRP",
      "roedt_stoettet": "Forslaget fra H, SP, VDL og FRP",
      "roedt_paa_vinner_side": true
    }
  ],
  "kommune": "verdal",
  "dato": "31.03.2025",
  "saksnummer_ps": "PS 18/25",
  "rodt_fremmet_forslag": false
}