{
  "tittel": "Årsmelding 2024 Verdal ungdomsråd",
  "innstilling": "Kommunedirektørens forslag til vedtak",
  "vedtak": "Årsmelding 2024 Verdal ungdomsråd tas til orientering.",
  "alternative_forslag": [],
  "voteringer": [
    {
      "beskrivelse": "Votering over kommunedirektørens forslag til vedtak",
      "alternativer": [
        {
          "navn": "For",
          "stemmer": "enstemmig"
        }
      ],
      "hvem_vant": "For",
      "roedt_stoettet": "For",
      "roedt_paa_vinner_side": true
    }
  ],
  "kommune": "verdal",
  "dato": "28.04.2025",
  "saksnummer_ps": "PS 44/25",
  "rodt_fremmet_forslag": false
}