{
  "tittel": "Anmodning om bosetting av flyktninger i 2026",
  "innstilling": "Ørland kommunestyre fatter følgende vedtak:\n1. Ørland kommune imøtekommer anmodningen fra Integrerings- og mangfoldsdirektoratet (IMDi) og vedtar å bosette inntil 35 flyktninger i 2026.\n2. Kommunen vurderer at den har kapasitet til å bosette totalt 35 flyktninger i 2026, også ved et eventuelt økt behov.\n3. Ørland kommune har per i dag ikke kapasitet til å bosette enslige mindreårige uten følgeperson, og vedtar derfor å ikke ta imot denne gruppen i 2026.\n4. Ørland kommune setter ubrukt integreringstilskudd for 2026 på fond for å dekke fremtidige utgifter knyttet til bosetting og integrering av flyktninger.",
  "vedtak": "Ørland kommunestyre fatter følgende vedtak:\n1. Ørland kommune imøtekommer anmodningen fra Integrerings- og mangfoldsdirektoratet (IMDi) og vedtar å bosette inntil 35 flyktninger i 2026.\n2. Kommunen vurderer at den har kapasitet til å bosette totalt 35 flyktninger i 2026, også ved et eventuelt økt behov.\n3. Ørland kommune har per i dag ikke kapasitet til å bosette enslige mindreårige uten følgeperson, og vedtar derfor å ikke ta imot denne gruppen i 2026.\n4. Ørland kommune setter ubrukt integreringstilskudd for 2026 på fond for å dekke fremtidige utgifter knyttet til bosetting og integrering av flyktninger.\n5. Ørland kommune skal tilrettelegge for språk praksis i alle kommunen sine enheter.",
  "alternative_forslag": [
    {
      "forslagsstiller": "Ann Elisabeth Solbue Valaas (SP)",
      "tekst": "Ørland kommune skal tilrettelegge for språk praksis i alle kommunen sine enheter."
    }
  ],
  "voteringer": [
    {
      "beskrivelse": "Votering over forslag - Opprinnelig forslag",
      "alternativer": [
        {
          "navn": "For",
          "stemmer": 29
        },
        {
          "navn": "Mot",
          "stemmer": 2
        }
      ],
      "hvem_vant": "For",
      "roedt_stoettet": "For",
      "roedt_side": "vinner"
    },
    {
      "beskrivelse": "Votering over forslag - Nytt punkt 5",
      "alternativer": [
        {
          "navn": "For",
          "stemmer": 29
        },
        {
          "navn": "Mot",
          "stemmer": 2
        }
      ],
      "hvem_vant": "For",
      "roedt_stoettet": "For",
      "roedt_side": "vinner"
    }
  ],
  "kommune": "ørland",
  "dato": "27.11.2025",
  "saksnummer_ps": "25/165",
  "rodt_fremmet_forslag": false
}