{
  "tittel": "Samlesak for referatsaker",
  "innstilling": "Sakene tas til orientering",
  "vedtak": "Sakene tas til orientering.",
  "alternative_forslag": [],
  "voteringer": [
    {
      "beskrivelse": "Votering om å ta sakene til orientering",
      "alternativer": [
        {
          "navn": "For",
          "stemmer": "enstemmig"
        }
      ],
      "hvem_vant": "For",
      "roedt_stoettet": "For",
      "roedt_paa_vinner_side": true
    }
  ],
  "kommune": "ørland",
  "dato": "30.10.2025",
  "saksnummer_ps": "25/128",
  "rodt_fremmet_forslag": false
}