{
  "tittel": "Prisbok for kultur og idrett 2026",
  "innstilling": "1. Sosiale og inkluderende rabatter\nKommunestyret vedtar at Ørland kommune viderefører studentrabatt ved bruk av kommunale svømmehaller og ishall, ved at studenter gis adgang til barnebillett. Ordningen synliggjøres tydelig i prisbok for kultur og idrett fra 2026.\nKommunestyret vedtar at personer med velferdspass gis adgang til kommunale svømmehaller og ishall til barnebillettpris. Vedtakene i sak «Kultur for alle» (17.11.2022) videreføres og legges til grunn også for enhet kultur og idrett\n2. Svømmeløft for barn\nKommunestyret vedtar at Ørland kommune innfører et svømmeløft med gratis inngang i kommunale svømmehaller for barn i siste år i barnehage og på 4. trinn, i følge med minst én betalende voksen. Ordningen innføres fra 01.02.2026. Kommunedirektøren legger til grunn at tiltaket har begrensede økonomiske konsekvenser, med estimert årlig inntektstap under 10.000 kroner, og vurderer dette som forsvarlig innenfor gjeldende rammer.",
  "vedtak": "1. Sosiale og inkluderende rabatter\nKommunestyret vedtar at Ørland kommune viderefører studentrabatt ved bruk av kommunale svømmehaller og ishall, ved at studenter gis adgang til barnebillett. Ordningen synliggjøres tydelig i prisbok for kultur og idrett fra 2026.\nKommunestyret vedtar at personer med velferdspass gis adgang til kommunale svømmehaller og ishall til barnebillettpris. Vedtakene i sak «Kultur for alle» (17.11.2022) videreføres og legges til grunn også for enhet kultur og idrett\n2. Svømmeløft for barn\nKommunestyret vedtar at Ørland kommune innfører et svømmeløft med gratis inngang i kommunale svømmehaller for barn i siste år i barnehage og på 4. trinn, i følge med minst én betalende voksen. Ordningen innføres fra 01.02.2026. Kommunedirektøren legger til grunn at tiltaket har begrensede økonomiske konsekvenser, med estimert årlig inntektstap under 10.000 kroner, og vurderer dette som forsvarlig innenfor gjeldende rammer.",
  "alternative_forslag": [],
  "voteringer": [
    {
      "beskrivelse": "Votering over forslag",
      "alternativer": [
        {
          "navn": "For",
          "stemmer": 29,
          "partier": {
            "AP": 7,
            "FRP": 2,
            "H": 6,
            "INP": 1,
            "MDG": 1,
            "Rødt": 1,
            "SP": 7,
            "SV": 1,
            "UAVHENGIG": 2,
            "V": 1
          }
        },
        {
          "navn": "Mot",
          "stemmer": 0
        }
      ],
      "hvem_vant": "For",
      "roedt_stoettet": "For",
      "roedt_paa_vinner_side": true
    }
  ],
  "kommune": "ørland",
  "dato": "22.01.2026",
  "saksnummer_ps": "26/006",
  "rodt_fremmet_forslag": false
}