{
  "tittel": "Sluttbehandling av detaljreguleringsplan 5016 Dullumslia",
  "innstilling": "Stjørdal kommune vedtar detaljreguleringsplan for Dullumslia med planID 5016, som vist på kart datert 06.11.2024, bestemmelser og beskrivelse datert 30.01.2025. Vedtaket fattes i henhold til plan- og bygningsloven § 12-12.",
  "vedtak": "Stjørdal kommune vedtar detaljreguleringsplan for Dullumslia med planID 5016, som vist på kart datert 06.11.2024, bestemmelser og beskrivelse datert 30.01.2025. Vedtaket fattes i henhold til plan- og bygningsloven § 12-12.",
  "alternative_forslag": [],
  "voteringer": [
    {
      "beskrivelse": "Votering over innstillingen om å vedta detaljreguleringsplan for Dullumslia.",
      "alternativer": [
        {
          "navn": "For innstillingen",
          "stemmer": 35
        },
        {
          "navn": "Mot innstillingen",
          "stemmer": 2
        }
      ],
      "vinner": "For innstillingen",
      "rodt": {
        "støttet": "For innstillingen",
        "var_vinner": true
      }
    }
  ],
  "kommune": "Stjørdal",
  "dato": "27.02.2025",
  "saksnummer_ps": "PS 16/2025",
  "rodt_fremmet_forslag": false
}