{
  "tittel": "Interpellasjon - Brukerstyrt personlig assistanse og tjenestetilbud til barn og unge",
  "innstilling": null,
  "vedtak": "Kommunestyret ber kommunedirektøren gjennomføre en helhetlig orientering på BPA-området i Melhus kommune, sett i sammenheng med øvrige helse- og omsorgstjenester i omsorgstrappa. Gjennomgangen skal blant annet omfatte saksbehandlingstid, vedtaksperioder, klagehåndtering, vurdering av barnets beste/brukerens beste samt praksis opp mot gjeldende lovverk og nasjonale føringer. Videre bes det om at saken inneholder konkrete forslag til endringer i praksis og organisering som kan sikre at BPA-tjenesten er i tråd med lovkrav, god forvaltningsskikk og intensjonen bak ordningen, samt hvordan disse endringene kan gjennomføres i praksis. Saken legges fram for politisk behandling senest 1. september 2026. Eventuelle tiltak som utløser kostnader legges inn i økonomi- og handlingsplanen som ikke-prioriterte tiltak. Saken sendes til utvalg for Helse, oppvekst og kultur.",
  "alternative_forslag": [
    {
      "forslagsstiller": "Rasmus Stafne Kjøsen (SV)",
      "tekst": "Kommunestyret ber kommunedirektøren gjennomføre en helhetlig orientering på BPA-området i Melhus kommune, sett i sammenheng med øvrige helse- og omsorgstjenester i omsorgstrappa. Gjennomgangen skal blant annet omfatte saksbehandlingstid, vedtaksperioder, klagehåndtering, vurdering av barnets beste/brukerens beste samt praksis opp mot gjeldende lovverk og nasjonale føringer. Videre bes det om at saken inneholder konkrete forslag til endringer i praksis og organisering som kan sikre at BPA-tjenesten er i tråd med lovkrav, god forvaltningsskikk og intensjonen bak ordningen, samt hvordan disse endringene kan gjennomføres i praksis. Saken legges fram for politisk behandling senest 1. september 2026. Eventuelle tiltak som utløser kostnader legges inn i økonomi- og handlingsplanen som ikke-prioriterte tiltak. Saken sendes til utvalg for Helse, oppvekst og kultur."
    }
  ],
  "voteringer": [
    {
      "beskrivelse": "Votering over forslaget fra Rasmus Stafne Kjøsen (SV)",
      "alternativer": [
        {
          "navn": "Forslaget fra Rasmus Stafne Kjøsen (SV)",
          "stemmer": 37
        }
      ],
      "vinner": "Forslaget fra Rasmus Stafne Kjøsen (SV)",
      "rodt": {
        "støttet": "Forslaget fra Rasmus Stafne Kjøsen (SV)",
        "var_vinner": true
      }
    }
  ],
  "kommune": "Malvik",
  "dato": "10.02.2026",
  "saksnummer_ps": "PS 10/26",
  "rodt_fremmet_forslag": false
}