{
  "tittel": "Søknad om fritak fra politiske verv - Arnstein Esphaug Moen",
  "innstilling": "Valgnemndas innstilling legges til grunn.",
  "vedtak": "Arnstein Esphaug Moen (AP) innvilges fritak fra sine politiske verv i kommunestyret, utvalg for teknikk og miljø og brukerutvalg for kollektivreisende i perioden 01.01.2025 – 30.04.2025. Vedtaket fattes jf Kommunelovens §7-9. Som fast representant for Arbeiderpartiet i kommunestyret inntrer Esten Bakke. Som ny første vara representant i utvalg for teknikk og miljø inntrer Hans Kristian Lilleberg. Som ny fast representant i brukerutvalg for kollektivreisende inntrer Ingunn Nervik Isaksen.",
  "alternative_forslag": [],
  "voteringer": [
    {
      "beskrivelse": "Votering over valgnemndas innstilling om fritak for Arnstein Esphaug Moen og oppnevning av nye representanter.",
      "alternativer": [
        {
          "navn": "Valgnemndas innstilling",
          "stemmer": "enstemmig"
        }
      ],
      "vinner": "Valgnemndas innstilling",
      "rodt": {
        "støttet": "Valgnemndas innstilling",
        "var_vinner": true
      }
    }
  ],
  "kommune": "Malvik",
  "dato": "11.02.2025",
  "saksnummer_ps": "PS 2/25",
  "rodt_fremmet_forslag": false
}