{
  "tittel": "Tilstandsrapport for grunnskolen i Malvik kommune 2024",
  "innstilling": "Tilstandsrapport for grunnskolen i Malvik kommune 2024 tas til orientering.",
  "vedtak": "Tilstandsrapport for grunnskolen i Malvik kommune 2024 tas til orientering.",
  "alternative_forslag": [],
  "voteringer": [
    {
      "beskrivelse": "Votering om innstillingen til tilstandsrapporten for grunnskolen i Malvik kommune 2024",
      "alternativer": [
        {
          "navn": "For innstillingen",
          "stemmer": 31
        }
      ],
      "vinner": "For innstillingen",
      "rodt": {
        "støttet": "For innstillingen",
        "var_vinner": true
      }
    }
  ],
  "kommune": "Malvik",
  "dato": "16.06.2025",
  "saksnummer_ps": "PS 61/25",
  "rodt_fremmet_forslag": false
}